<?xml version="1.0" encoding="UTF-8"?>
<movie>
   <name>Covenant, The</name>
   <company>Columbia Pictures / Sony Pictures Releasing</company>
   <genres>
      <genre>Horror</genre>
      <genre>SuspenseThriller</genre>
   </genres>
   <authors>
      <author>J.S. Cardone</author>
   </authors>
   <directors>
      <director>Renny Harlin</director>
   </directors>
   <origins>
      <origin>USA</origin>
   </origins>
   <actors>
      <actor>Steven Strait</actor>
      <actor>Sebastian Stan</actor>
      <actor>Toby Hemingway</actor>
      <actor>Chace Crawford</actor>
      <actor>Taylor Kitsch</actor>
      <actor>Laura Ramsey</actor>
      <actor>Jessica Lucas</actor>
      <actor>Wendy Crewson</actor>
   </actors>
   <release_date>September 8, 2006</release_date>
   <running_time>97</running_time>
   <rating>PG-13</rating>
   <reviews>
      <review>
         <snippet>Harlin, with his customary visual brio, has created a film that is deliriously watchable. It's just not all that interesting. In the end, The Covenant is simply a glossier version of TV's "Charmed."</snippet>
         <url>http://ae.philly.com/entertainment/ui/philly/movie.html?id=694267&amp;reviewId=21444</url>
         <critic>David Hiltbrand</critic>
      </review>
      <review>
         <snippet>Utterly stupid and full of lazy plotting and lazier dialogue, this is just idiotic enough to entertain on nights when you want to give your brain a rest.</snippet>
         <url>http://www.empireonline.com/reviews/review.asp?FID=11304</url>
         <critic>Helen O&amp;#039;Hara</critic>
      </review>
      <review>
         <snippet>Profoundly mediocre supernatural thriller.</snippet>
         <url>http://www.nydailynews.com/entertainment/movies/moviereviews/story/450823p-379338c.html</url>
         <critic>Elizabeth Weitzman</critic>
      </review>
      <review>
         <snippet>When the villain is revealed, you are neither surprised nor scared. You just think, "That guy?"</snippet>
         <url>http://www.nypost.com/entertainment/movies/abercrombie__witch_movies_kyle_smith.htm</url>
         <critic>Kyle Smith</critic>
      </review>
      <review>
         <snippet>The Covenant is dopey, formulaic stuff for the Friday night fright crowd. Worse for them, it's never remotely scary.</snippet>
         <url>http://www.boston.com/ae/movies/articles/2006/09/09/formulaic_covenant_is_more_dopey_than_scary/</url>
         <critic>Ty Burr</critic>
      </review>
      <review>
         <snippet>Okay, so it isn't challenging. There are worse things for a horror-thriller about supernatural high-schoolers to not be. Like not scary. Or not thrilling. Or not as entertaining as an episode of "Charmed."</snippet>
         <url>http://www.avclub.com/content/node/52887</url>
         <critic>Amelie Gillette</critic>
      </review>
      <review>
         <snippet>The idiocy and sheer laziness of the whole concept ought to be the sort of thing director Renny Harlin (Deep Blue Sea) could make into glorious cinematic cheese, and occasionally he cuts loose with a swarm of CGI spiders or a final battle that resembles nothing more than a live action game of "Street Fighter II." But he's hamstrung by the PG-13 rating and the budget.</snippet>
         <url>http://www.laweekly.com/film+tv/film-reviews/film-reviews/14428/</url>
         <critic>Luke Y. Thompson</critic>
      </review>
      <review>
         <snippet>As boredom sets in, the viewer realizes that "The Covenant" does possess one magical power: It afflicts its audience with restless leg syndrome.</snippet>
         <url>http://www.calendarlive.com/movies/reviews/cl-et-covenant11sep11,0,5828292.story</url>
         <critic>Michael Ordona</critic>
      </review>
      <review>
         <snippet>For the most part, the proceedings are slow, solemn and tedious.</snippet>
         <url>http://www.hollywoodreporter.com/thr/reviews/review_display.jsp?vnu_content_id=1003119259</url>
         <critic>Frank Scheck</critic>
      </review>
      <review>
         <snippet>It fails utterly as a horror picture, although it delivers plenty of PG-13-rated flesh and unintentional laughs.</snippet>
         <url>http://online.tvguide.com/newsearch/detail.aspx?tvobjectid=282701&amp;more=ucmoviereview</url>
         <critic>Maitland McDonagh</critic>
      </review>
      <review>
         <snippet>Muddled and most unmagical offering.</snippet>
         <url>http://www.variety.com/review/VE1117931515?categoryid=31&amp;cs=1</url>
         <critic>Justin Chang</critic>
      </review>
      <review>
         <snippet>Cobbled-together teenybopper tripe.</snippet>
         <url>http://www.ew.com/ew/article/review/movie/0,6115,1534380_1_0_,00.html</url>
         <critic>Gregory Kirshling</critic>
      </review>
      <review>
         <snippet>Surely nothing Hollywood did in its darkest, most debauched hour could possibly justify the penance we're paying that allows Harlin to continue directing movies.</snippet>
         <url>http://www.austinchronicle.com/gyrobase/Calendar/Film?Film=oid%3A400617</url>
         <critic>Josh Rosenblatt</critic>
      </review>
      <review>
         <snippet>Crushingly dull teen horror flick.</snippet>
         <url>http://onfilm.chicagoreader.com/movies/briefs/30278_COVENANT.html</url>
         <critic>Reece Pendleton</critic>
      </review>
      <review>
         <snippet>Director Renny Harlin, whose colon-studded credits include "Die Hard 2: Die Harder" and "Exorcist: The Beginning," knows the deal here: Pay homoerotic homage to youth and beauty, crank up the heavy metal on the soundtrack, and spare no effort to backlight the omnipresent rain.</snippet>
         <url>http://www.washingtonpost.com/ac2/wp-dyn?node=cityguide/profile&amp;id=1115179&amp;categories=Movies&amp;nm=1</url>
         <critic>Desson Thomson</critic>
      </review>
      <review>
         <snippet>That's the one with a car that explodes and gets put back together by magic, right?  Yeah, that’s pretty much the coolest part.</snippet>
         <url>http://movies2.nytimes.com/2006/09/09/movies/09cove.html?ref=movies</url>
         <critic>Nathan Lee</critic>
      </review>
   </reviews>
   <US_Gross>$23,364,784</US_Gross>
   <production_budget>$20,000,000</production_budget>
   <weekend_gross>$8,852,458</weekend_gross>
   <number_of_screens>2,681</number_of_screens>
   <summer_release>false</summer_release>
   <christmas_release>false</christmas_release>
   <memorial_release>false</memorial_release>
   <independence_release>false</independence_release>
   <labor_release>false</labor_release>
</movie>